sphinxcontrib/__init__.py
sphinxcontrib/versioning/__init__.py
sphinxcontrib/versioning/__main__.py
sphinxcontrib/versioning/git.py
sphinxcontrib/versioning/lib.py
sphinxcontrib/versioning/routines.py
sphinxcontrib/versioning/setup_logging.py
sphinxcontrib/versioning/sphinx_.py
sphinxcontrib/versioning/versions.py
sphinxcontrib/versioning/_static/banner.css
sphinxcontrib/versioning/_templates/banner.html
sphinxcontrib/versioning/_templates/versions.html
sphinx_versions-1.1.3.dist-info/LICENSE
sphinx_versions-1.1.3.dist-info/METADATA
sphinx_versions-1.1.3.dist-info/WHEEL
sphinx_versions-1.1.3.dist-info/entry_points.txt
sphinx_versions-1.1.3.dist-info/top_level.txt
sphinx_versions-1.1.3.dist-info/RECORD
